rayforge/__init__.py
rayforge/api/__init__.py
rayforge/api/huggingface_api.py
rayforge/api/openai_api.py
rayforge/api/replicate_api.py
rayforge/cli/__init__.py
rayforge/cli/main.py
rayforge/core/__init__.py
rayforge/core/forge_engine.py
rayforge/core/metricizer.py
rayforge/core/model_runner.py
rayforge/dashboard/__init__.py
rayforge/dashboard/app.py
rayforge/dashboard/plotter.py
rayforge/deployment/__init__.py
rayforge/deployment/dockerize.py
rayforge/deployment/gui_streamlit.py
rayforge/deployment/serve_fastapi.py
rayforge/utils/__init__.py
rayforge/utils/constants.py
rayforge/utils/io.py
rayforge/utils/logger.py
rayforge_ai-0.1.0.dist-info/METADATA
rayforge_ai-0.1.0.dist-info/WHEEL
rayforge_ai-0.1.0.dist-info/entry_points.txt
rayforge_ai-0.1.0.dist-info/top_level.txt
rayforge_ai-0.1.0.dist-info/RECORD
