Metadata-Version: 2.4
Name: rayforge-ai
Version: 0.1.0
Summary: Universal Python framework to download, run, and metricize AI models
Home-page: https://github.com/rayken-ai/rayforge
Author: Rayken AI
Author-email: founder@rayken.ai
License: MIT
Classifier: Programming Language :: Python :: 3.10
Classifier: License :: OSI Approved :: MIT License
Classifier: Operating System :: OS Independent
Requires-Python: >=3.8
Requires-Dist: transformers>=4.38.0
Requires-Dist: torch>=2.2.0
Requires-Dist: huggingface_hub>=0.20.0
Requires-Dist: openai>=1.24.0
Requires-Dist: replicate>=0.25.0
Requires-Dist: fastapi>=0.110.0
Requires-Dist: uvicorn[standard]>=0.29.0
Requires-Dist: streamlit>=1.34.0
Requires-Dist: typer[all]>=0.12.3
Requires-Dist: python-dotenv>=1.0.1
Requires-Dist: pandas>=2.2.0
Requires-Dist: scikit-learn>=1.4.0
Requires-Dist: matplotlib>=3.8.0
Requires-Dist: seaborn>=0.13.0
Requires-Dist: requests>=2.31.0
Requires-Dist: tqdm>=4.66.0
Requires-Dist: aiohttp>=3.9.0
Requires-Dist: pydantic>=2.6.0
Requires-Dist: tabulate>=0.9.0
Provides-Extra: dev
Requires-Dist: pytest; extra == "dev"
Requires-Dist: ruff; extra == "dev"
Dynamic: author
Dynamic: author-email
Dynamic: classifier
Dynamic: description
Dynamic: description-content-type
Dynamic: home-page
Dynamic: license
Dynamic: provides-extra
Dynamic: requires-dist
Dynamic: requires-python
Dynamic: summary
